growler_ext/SassMiddleware.py
growler_sass/__init__.py
growler_sass/__meta__.py
growler_sass/middleware.py
growler_sass-0.1.0.dist-info/DESCRIPTION.rst
growler_sass-0.1.0.dist-info/METADATA
growler_sass-0.1.0.dist-info/RECORD
growler_sass-0.1.0.dist-info/WHEEL
growler_sass-0.1.0.dist-info/metadata.json
growler_sass-0.1.0.dist-info/top_level.txt
